sundialy/__init__.py
sundialy/analemmatic.py
sundialy/py.typed
sundialy/tools/__init__.py
sundialy/tools/bird.py
sundialy/tools/constants.py
sundialy/tools/sampa.py
sundialy/tools/solpos.py
sundialy/tools/spa.py
sundialy-0.0.1.dist-info/METADATA
sundialy-0.0.1.dist-info/WHEEL
sundialy-0.0.1.dist-info/licenses/LICENSE
sundialy-0.0.1.dist-info/RECORD
