Metadata-Version: 2.1
Name: sundialy
Version: 0.0.1
Summary: A sundial library for python
Project-URL: Homepage, https://github.com/AttackingOrDefending/sundialy
Project-URL: Documentation, https://sundialy.readthedocs.io
Project-URL: Bug Tracker, https://github.com/AttackingOrDefending/sundialy/issues
License-File: LICENSE
Keywords: analemmatic,astronomy,sun,sundial,sundials
Classifier: Intended Audience :: Developers
Classifier: Intended Audience :: Science/Research
Classifier: License :: OSI Approved :: MIT License
Classifier: Operating System :: OS Independent
Classifier: Programming Language :: Python :: 3
Classifier: Topic :: Software Development :: Libraries
Classifier: Typing :: Typed
Requires-Python: >=3.7
Requires-Dist: matplotlib>=3.5.0
Requires-Dist: shapely>=1.8.0
